Metadata-Version: 1.0
Name: ici2
Version: 0.5.0
Summary: translate english to chinese dictionary 
Home-page: https://github.com/realhu1989/ici
Author: realhu1989 yuzhe
Author-email: huyunyan@live.cn
License: UNKNOWN
Keywords: python iciba dictionary terminal translate translation
Platform: UNKNOWN
